LICENSE
MANIFEST.in
README.md
setup.py
simple_paginator/__init__.py
simple_paginator/tests.py
simple_paginator.egg-info/PKG-INFO
simple_paginator.egg-info/SOURCES.txt
simple_paginator.egg-info/dependency_links.txt
simple_paginator.egg-info/top_level.txt
simple_paginator/templates/simple_paginator/paginator_control.html
simple_paginator/templates/simple_paginator/paginator_header.html
simple_paginator/templatetags/__init__.py
simple_paginator/templatetags/helpers.py