Metadata-Version: 1.1
Name: simple-paginator
Version: 0.3.0
Summary: A simple wrapper around the Django paginator
Home-page: https://github.com/dbrgn/django-simplepaginator
Author: Danilo Bargen
Author-email: gezuru@gmail.com
License: LGPLv3
Keywords: django simple pagination paginator
Platform: any
Classifier: Development Status :: 4 - Beta
Classifier: Environment :: Web Environment
Classifier: Framework :: Django
Classifier: Intended Audience :: Developers
Classifier: License :: OSI Approved :: GNU Library or Lesser General Public License (LGPL)
Classifier: Operating System :: OS Independent
Classifier: Programming Language :: Python :: 2
Classifier: Topic :: Internet :: WWW/HTTP
Classifier: Topic :: Software Development :: Libraries :: Python Modules
